dq_validation-0.1.8.dist-info/METADATA
dq_validation-0.1.8.dist-info/WHEEL
dq_validation/__init__.py
dq_validation/_validate.cpython-310-darwin.so
dq_validation/config.py
dq_validation/default.py
dq_validation/error.py
dq_validation/logger.py
dq_validation/schemas/__init__.py
dq_validation/schemas/_generated/__init__.py
dq_validation/schemas/_generated/validation_config.py
dq_validation/schemas/_generated/validation_report.py
dq_validation/spark.py
dq_validation/spark_utils.py
dq_validation/utils.py
dq_validation/validate.py
dq_validation-0.1.8.dist-info/RECORD
