Metadata-Version: 2.4
Name: dq_validation
Version: 0.1.8
Classifier: Programming Language :: Rust
Classifier: Programming Language :: Python :: Implementation :: CPython
Classifier: Programming Language :: Python :: Implementation :: PyPy
Requires-Dist: pandas>=2.1.1,<2.2.0
Requires-Dist: pyspark>=3.5.0
Requires-Dist: pyarrow>=14.0.0,<14.1.0
Requires-Dist: pydantic>=2.7.0,<2.8.0
Requires-Dist: numpy>=1.26.1
Requires-Dist: decentriq-util==0.1.0.dev13
Requires-Dist: psutil>=5.9.6
Requires-Dist: pytest>=8.3.3 ; extra == 'test'
Provides-Extra: test
Requires-Python: >=3.10
